wealthsimple/__init__.py
wealthsimple/wealthsimple.py
Wealthsimple_API_Python-0.1.0.dist-info/LICENSE
Wealthsimple_API_Python-0.1.0.dist-info/METADATA
Wealthsimple_API_Python-0.1.0.dist-info/WHEEL
Wealthsimple_API_Python-0.1.0.dist-info/top_level.txt
Wealthsimple_API_Python-0.1.0.dist-info/RECORD
