Metadata-Version: 2.1
Name: Wealthsimple-API-Python
Version: 0.1.0
Summary: Python wrapper for the Wealthsimple Trade API
Home-page: https://github.com/noahwoodin/Wealthsimple-API-Python
Author: Noah Woodin
Author-email: noahwoodin1@gmail.com
License: MIT
Keywords: wealthsimple,trade,finance,DRIP,dividend,buy,stocks,market,api,wrapper
Platform: UNKNOWN
Classifier: Programming Language :: Python :: 3
Classifier: License :: OSI Approved :: MIT License
Classifier: Operating System :: OS Independent
License-File: LICENSE
Requires-Dist: requests
Requires-Dist: pyotp
Requires-Dist: certifi
